google/shopping/merchant_quota/__init__.py
google/shopping/merchant_quota/gapic_version.py
google/shopping/merchant_quota/py.typed
google/shopping/merchant_quota_v1/__init__.py
google/shopping/merchant_quota_v1/gapic_metadata.json
google/shopping/merchant_quota_v1/gapic_version.py
google/shopping/merchant_quota_v1/py.typed
google/shopping/merchant_quota_v1/services/__init__.py
google/shopping/merchant_quota_v1/services/account_limits_service/__init__.py
google/shopping/merchant_quota_v1/services/account_limits_service/async_client.py
google/shopping/merchant_quota_v1/services/account_limits_service/client.py
google/shopping/merchant_quota_v1/services/account_limits_service/pagers.py
google/shopping/merchant_quota_v1/services/account_limits_service/transports/__init__.py
google/shopping/merchant_quota_v1/services/account_limits_service/transports/base.py
google/shopping/merchant_quota_v1/services/account_limits_service/transports/grpc.py
google/shopping/merchant_quota_v1/services/account_limits_service/transports/grpc_asyncio.py
google/shopping/merchant_quota_v1/services/account_limits_service/transports/rest.py
google/shopping/merchant_quota_v1/services/account_limits_service/transports/rest_base.py
google/shopping/merchant_quota_v1/services/quota_service/__init__.py
google/shopping/merchant_quota_v1/services/quota_service/async_client.py
google/shopping/merchant_quota_v1/services/quota_service/client.py
google/shopping/merchant_quota_v1/services/quota_service/pagers.py
google/shopping/merchant_quota_v1/services/quota_service/transports/__init__.py
google/shopping/merchant_quota_v1/services/quota_service/transports/base.py
google/shopping/merchant_quota_v1/services/quota_service/transports/grpc.py
google/shopping/merchant_quota_v1/services/quota_service/transports/grpc_asyncio.py
google/shopping/merchant_quota_v1/services/quota_service/transports/rest.py
google/shopping/merchant_quota_v1/services/quota_service/transports/rest_base.py
google_shopping_merchant_quota-1.2.0.dist-info/licenses/LICENSE
google_shopping_merchant_quota-1.2.0.dist-info/METADATA
google_shopping_merchant_quota-1.2.0.dist-info/WHEEL
google_shopping_merchant_quota-1.2.0.dist-info/top_level.txt
google_shopping_merchant_quota-1.2.0.dist-info/RECORD
